daily_summary/__init__.py
daily_summary/generate_daily_summary.py
daily_summary/git_data_extract.py
daily_summary/main.py
daily_summary/summarize_diff.py
tests/__init__.py
tests/main_test.py
tests/test_main.py
daily_summary-0.1.29.dist-info/METADATA
daily_summary-0.1.29.dist-info/WHEEL
daily_summary-0.1.29.dist-info/entry_points.txt
daily_summary-0.1.29.dist-info/top_level.txt
daily_summary-0.1.29.dist-info/RECORD
