Metadata-Version: 2.1
Name: daily-summary
Version: 0.1.29
Summary: A package to generate daily development reports
Home-page: https://github.com/jdriscoll98/daily-summary
Author: Jack Driscoll
Author-email: jackdriscoll777@gmail.com
Requires-Python: >=3
Requires-Dist: openai
Requires-Dist: gitpython
Requires-Dist: python-dotenv
Requires-Dist: pytest
